{"trial_id": "04", "hyperparameters": {"space": [{"class_name": "Int", "config": {"name": "num_layers", "default": null, "conditions": [], "min_value": 1, "max_value": 4, "step": 1, "sampling": "linear"}}, {"class_name": "Int", "config": {"name": "units_0", "default": null, "conditions": [], "min_value": 200, "max_value": 600, "step": 50, "sampling": "linear"}}, {"class_name": "Choice", "config": {"name": "activation", "default": "relu", "conditions": [], "values": ["relu"], "ordered": false}}, {"class_name": "Float", "config": {"name": "L1_0", "default": 1e-12, "conditions": [], "min_value": 1e-12, "max_value": 1e-06, "step": null, "sampling": "log"}}, {"class_name": "Float", "config": {"name": "drop_0", "default": 0.0, "conditions": [], "min_value": 0.0, "max_value": 0.1, "step": null, "sampling": "linear"}}, {"class_name": "Float", "config": {"name": "lr", "default": 1e-07, "conditions": [], "min_value": 1e-07, "max_value": 0.0001, "step": null, "sampling": "log"}}, {"class_name": "Int", "config": {"name": "units_1", "default": null, "conditions": [], "min_value": 200, "max_value": 600, "step": 50, "sampling": "linear"}}, {"class_name": "Float", "config": {"name": "L1_1", "default": 1e-12, "conditions": [], "min_value": 1e-12, "max_value": 1e-06, "step": null, "sampling": "log"}}, {"class_name": "Float", "config": {"name": "drop_1", "default": 0.0, "conditions": [], "min_value": 0.0, "max_value": 0.1, "step": null, "sampling": "linear"}}, {"class_name": "Int", "config": {"name": "units_2", "default": null, "conditions": [], "min_value": 200, "max_value": 600, "step": 50, "sampling": "linear"}}, {"class_name": "Float", "config": {"name": "L1_2", "default": 1e-12, "conditions": [], "min_value": 1e-12, "max_value": 1e-06, "step": null, "sampling": "log"}}, {"class_name": "Float", "config": {"name": "drop_2", "default": 0.0, "conditions": [], "min_value": 0.0, "max_value": 0.1, "step": null, "sampling": "linear"}}, {"class_name": "Int", "config": {"name": "units_3", "default": null, "conditions": [], "min_value": 200, "max_value": 600, "step": 50, "sampling": "linear"}}, {"class_name": "Float", "config": {"name": "L1_3", "default": 1e-12, "conditions": [], "min_value": 1e-12, "max_value": 1e-06, "step": null, "sampling": "log"}}, {"class_name": "Float", "config": {"name": "drop_3", "default": 0.0, "conditions": [], "min_value": 0.0, "max_value": 0.1, "step": null, "sampling": "linear"}}], "values": {"num_layers": 4, "units_0": 400, "activation": "relu", "L1_0": 6.232929500561039e-08, "drop_0": 0.08144781454478105, "lr": 2.7290311036945276e-07, "units_1": 300, "L1_1": 1.0855316306557266e-09, "drop_1": 0.014472055263366847, "units_2": 400, "L1_2": 2.4501167673100346e-08, "drop_2": 0.01995887063541001, "units_3": 550, "L1_3": 7.511536883470177e-12, "drop_3": 0.03974888769814575}}, "metrics": {"metrics": {"auc": {"direction": "max", "observations": [{"value": [0.6928052504857382], "step": 1}]}, "loss": {"direction": "min", "observations": [{"value": [0.2356849660476049], "step": 1}]}, "macro_f1_score": {"direction": "min", "observations": [{"value": [0.14209536214669546], "step": 1}]}, "val_auc": {"direction": "max", "observations": [{"value": [0.7253466049830118], "step": 1}]}, "val_loss": {"direction": "min", "observations": [{"value": [0.2274974783261617], "step": 1}]}, "val_macro_f1_score": {"direction": "max", "observations": [{"value": [0.10308115929365158], "step": 1}]}}}, "score": 0.10308115929365158, "best_step": 1, "status": "COMPLETED", "message": null}