{"trial_id": "43", "hyperparameters": {"space": [{"class_name": "Int", "config": {"name": "num_layers", "default": null, "conditions": [], "min_value": 1, "max_value": 4, "step": 1, "sampling": "linear"}}, {"class_name": "Int", "config": {"name": "units_0", "default": null, "conditions": [], "min_value": 200, "max_value": 600, "step": 50, "sampling": "linear"}}, {"class_name": "Choice", "config": {"name": "activation", "default": "relu", "conditions": [], "values": ["relu"], "ordered": false}}, {"class_name": "Float", "config": {"name": "L1_0", "default": 1e-12, "conditions": [], "min_value": 1e-12, "max_value": 1e-06, "step": null, "sampling": "log"}}, {"class_name": "Float", "config": {"name": "lr", "default": 1e-07, "conditions": [], "min_value": 1e-07, "max_value": 0.0001, "step": null, "sampling": "log"}}, {"class_name": "Int", "config": {"name": "units_1", "default": null, "conditions": [], "min_value": 200, "max_value": 600, "step": 50, "sampling": "linear"}}, {"class_name": "Float", "config": {"name": "L1_1", "default": 1e-12, "conditions": [], "min_value": 1e-12, "max_value": 1e-06, "step": null, "sampling": "log"}}, {"class_name": "Int", "config": {"name": "units_2", "default": null, "conditions": [], "min_value": 200, "max_value": 600, "step": 50, "sampling": "linear"}}, {"class_name": "Float", "config": {"name": "L1_2", "default": 1e-12, "conditions": [], "min_value": 1e-12, "max_value": 1e-06, "step": null, "sampling": "log"}}, {"class_name": "Int", "config": {"name": "units_3", "default": null, "conditions": [], "min_value": 200, "max_value": 600, "step": 50, "sampling": "linear"}}, {"class_name": "Float", "config": {"name": "L1_3", "default": 1e-12, "conditions": [], "min_value": 1e-12, "max_value": 1e-06, "step": null, "sampling": "log"}}], "values": {"num_layers": 1, "units_0": 600, "activation": "relu", "L1_0": 1e-12, "lr": 0.0001, "units_1": 200, "L1_1": 1e-06, "units_2": 600, "L1_2": 1e-06, "units_3": 200, "L1_3": 1e-06}}, "metrics": {"metrics": {"auc": {"direction": "max", "observations": [{"value": [0.9147348602612814], "step": 0}]}, "loss": {"direction": "min", "observations": [{"value": [0.12441244224707286], "step": 0}]}, "macro_f1_score": {"direction": "min", "observations": [{"value": [0.2604917188485463], "step": 0}]}, "val_auc": {"direction": "max", "observations": [{"value": [0.9511566956837972], "step": 0}]}, "val_loss": {"direction": "min", "observations": [{"value": [0.0742222045858701], "step": 0}]}, "val_macro_f1_score": {"direction": "max", "observations": [{"value": [0.310875803232193], "step": 0}]}}}, "score": 0.310875803232193, "best_step": 0, "status": "COMPLETED", "message": null}