{"trial_id": "05", "hyperparameters": {"space": [{"class_name": "Int", "config": {"name": "num_layers", "default": null, "conditions": [], "min_value": 1, "max_value": 4, "step": 1, "sampling": "linear"}}, {"class_name": "Int", "config": {"name": "units_0", "default": null, "conditions": [], "min_value": 200, "max_value": 600, "step": 50, "sampling": "linear"}}, {"class_name": "Choice", "config": {"name": "activation", "default": "relu", "conditions": [], "values": ["relu"], "ordered": false}}, {"class_name": "Float", "config": {"name": "L1_0", "default": 1e-12, "conditions": [], "min_value": 1e-12, "max_value": 1e-06, "step": null, "sampling": "log"}}, {"class_name": "Float", "config": {"name": "drop_0", "default": 0.0, "conditions": [], "min_value": 0.0, "max_value": 0.1, "step": null, "sampling": "linear"}}, {"class_name": "Float", "config": {"name": "lr", "default": 1e-07, "conditions": [], "min_value": 1e-07, "max_value": 0.0001, "step": null, "sampling": "log"}}, {"class_name": "Int", "config": {"name": "units_1", "default": null, "conditions": [], "min_value": 200, "max_value": 600, "step": 50, "sampling": "linear"}}, {"class_name": "Float", "config": {"name": "L1_1", "default": 1e-12, "conditions": [], "min_value": 1e-12, "max_value": 1e-06, "step": null, "sampling": "log"}}, {"class_name": "Float", "config": {"name": "drop_1", "default": 0.0, "conditions": [], "min_value": 0.0, "max_value": 0.1, "step": null, "sampling": "linear"}}, {"class_name": "Int", "config": {"name": "units_2", "default": null, "conditions": [], "min_value": 200, "max_value": 600, "step": 50, "sampling": "linear"}}, {"class_name": "Float", "config": {"name": "L1_2", "default": 1e-12, "conditions": [], "min_value": 1e-12, "max_value": 1e-06, "step": null, "sampling": "log"}}, {"class_name": "Float", "config": {"name": "drop_2", "default": 0.0, "conditions": [], "min_value": 0.0, "max_value": 0.1, "step": null, "sampling": "linear"}}, {"class_name": "Int", "config": {"name": "units_3", "default": null, "conditions": [], "min_value": 200, "max_value": 600, "step": 50, "sampling": "linear"}}, {"class_name": "Float", "config": {"name": "L1_3", "default": 1e-12, "conditions": [], "min_value": 1e-12, "max_value": 1e-06, "step": null, "sampling": "log"}}, {"class_name": "Float", "config": {"name": "drop_3", "default": 0.0, "conditions": [], "min_value": 0.0, "max_value": 0.1, "step": null, "sampling": "linear"}}], "values": {"num_layers": 1, "units_0": 250, "activation": "relu", "L1_0": 3.3594461633856276e-10, "drop_0": 0.09123433593597492, "lr": 4.369227521751818e-06, "units_1": 500, "L1_1": 1.6732693684198854e-10, "drop_1": 0.019453724793318108, "units_2": 350, "L1_2": 2.6538015881989694e-10, "drop_2": 0.014566925510413033, "units_3": 450, "L1_3": 7.745103724509008e-12, "drop_3": 0.09790501200727744}}, "metrics": {"metrics": {"auc": {"direction": "max", "observations": [{"value": [0.8960544268290201], "step": 0}]}, "loss": {"direction": "min", "observations": [{"value": [0.1419177974263827], "step": 0}]}, "macro_f1_score": {"direction": "min", "observations": [{"value": [0.32669590910275775], "step": 0}]}, "val_auc": {"direction": "max", "observations": [{"value": [0.9524317979812622], "step": 0}]}, "val_loss": {"direction": "min", "observations": [{"value": [0.10669853289922078], "step": 0}]}, "val_macro_f1_score": {"direction": "max", "observations": [{"value": [0.38334118326505023], "step": 0}]}}}, "score": 0.38334118326505023, "best_step": 0, "status": "COMPLETED", "message": null}